IProgress/__init__.py
IProgress/progressbar.py
IProgress/widgets.py
IProgress-0.4.dist-info/DESCRIPTION.rst
IProgress-0.4.dist-info/METADATA
IProgress-0.4.dist-info/RECORD
IProgress-0.4.dist-info/WHEEL
IProgress-0.4.dist-info/metadata.json
IProgress-0.4.dist-info/top_level.txt
